mutahunter/__init__.py
mutahunter/main.py
mutahunter/core/__init__.py
mutahunter/core/analyzer.py
mutahunter/core/controller.py
mutahunter/core/exceptions.py
mutahunter/core/io.py
mutahunter/core/llm_mutation_engine.py
mutahunter/core/logger.py
mutahunter/core/parsers.py
mutahunter/core/prompt_factory.py
mutahunter/core/report.py
mutahunter/core/router.py
mutahunter/core/runner.py
mutahunter/core/utils.py
mutahunter/core/entities/__init__.py
mutahunter/core/entities/config.py
mutahunter/core/queries/__init__.py
mutahunter/core/queries/tree-sitter-c-tags.scm
mutahunter/core/queries/tree-sitter-c_sharp-tags.scm
mutahunter/core/queries/tree-sitter-cpp-tags.scm
mutahunter/core/queries/tree-sitter-go-tags.scm
mutahunter/core/queries/tree-sitter-java-tags.scm
mutahunter/core/queries/tree-sitter-javascript-tags.scm
mutahunter/core/queries/tree-sitter-php-tags.scm
mutahunter/core/queries/tree-sitter-python-tags.scm
mutahunter/core/queries/tree-sitter-ruby-tags.scm
mutahunter/core/queries/tree-sitter-rust-tags.scm
mutahunter/core/queries/tree-sitter-typescript-tags.scm
mutahunter/core/templates/mutant_generation/mutator_system.txt
mutahunter/core/templates/mutant_generation/mutator_user.txt
mutahunter/core/templates/utils/yaml_fixer_user.txt
mutahunter-1.3.2.dist-info/licenses/LICENSE
mutahunter-1.3.2.dist-info/METADATA
mutahunter-1.3.2.dist-info/WHEEL
mutahunter-1.3.2.dist-info/entry_points.txt
mutahunter-1.3.2.dist-info/top_level.txt
mutahunter-1.3.2.dist-info/RECORD
