Metadata-Version: 2.4
Name: mutahunter
Version: 1.3.2
Summary: LLM Mutation Testing for any programming language
Author: Steven Jung
Maintainer: Steven Jung
License:                     GNU AFFERO GENERAL PUBLIC LICENSE
Project-URL: Repository, https://github.com/codeintegrity-ai/mutahunter
Keywords: mutahunter,test,testing,LLM,mutant
Requires-Python: >=3.11
License-File: LICENSE
Requires-Dist: tree-sitter==0.21.3
Requires-Dist: tree_sitter_languages==1.10.2
Requires-Dist: tqdm
Requires-Dist: jinja2
Requires-Dist: litellm
Provides-Extra: dev
Requires-Dist: isort; extra == "dev"
Requires-Dist: black; extra == "dev"
Provides-Extra: testing
Requires-Dist: pytest; extra == "testing"
Dynamic: license-file
